db_query_agent/__init__.py
db_query_agent/agent.py
db_query_agent/agent_integration.py
db_query_agent/cache_manager.py
db_query_agent/config.py
db_query_agent/connection_manager.py
db_query_agent/exceptions.py
db_query_agent/query_validator.py
db_query_agent/schema_extractor.py
db_query_agent/session_manager.py
db_query_agent/simple_multi_agent_system.py
db_query_agent/agents/__init__.py
db_query_agent/agents/simple_conversational_agent.py
db_query_agent/agents/simple_sql_agent.py
db_query_agent/tools/__init__.py
db_query_agent/tools/conversation_tools.py
db_query_agent/tools/sql_tools.py
db_query_agent-0.1.4.dist-info/licenses/LICENSE
db_query_agent-0.1.4.dist-info/METADATA
db_query_agent-0.1.4.dist-info/WHEEL
db_query_agent-0.1.4.dist-info/top_level.txt
db_query_agent-0.1.4.dist-info/RECORD
