Metadata-Version: 2.4
Name: db-query-agent
Version: 0.1.4
Summary: AI-powered natural language database query system using OpenAI Agents SDK
Author-email: Paul Awolesi <awolesiboluwatife@gmail.com>
License: MIT
Project-URL: Homepage, https://github.com/Ocolus1/db-query-agent
Project-URL: Documentation, https://github.com/Ocolus1/db-query-agent#readme
Project-URL: Repository, https://github.com/Ocolus1/db-query-agent
Project-URL: Issues, https://github.com/Ocolus1/db-query-agent/issues
Keywords: ai,database,natural-language,sql,openai,agents,text-to-sql
Classifier: Development Status :: 3 - Alpha
Classifier: Intended Audience :: Developers
Classifier: License :: OSI Approved :: MIT License
Classifier: Programming Language :: Python :: 3
Classifier: Programming Language :: Python :: 3.10
Classifier: Programming Language :: Python :: 3.11
Classifier: Programming Language :: Python :: 3.12
Classifier: Topic :: Database
Classifier: Topic :: Scientific/Engineering :: Artificial Intelligence
Requires-Python: >=3.10
License-File: LICENSE
Requires-Dist: openai-agents>=0.4.0
Requires-Dist: sqlalchemy>=2.0.0
Requires-Dist: sqlparse>=0.5.0
Requires-Dist: pydantic>=2.0.0
Requires-Dist: python-dotenv>=1.0.0
Requires-Dist: aiosqlite>=0.19.0
Provides-Extra: postgres
Requires-Dist: psycopg2-binary>=2.9.0; extra == "postgres"
Requires-Dist: asyncpg>=0.29.0; extra == "postgres"
Provides-Extra: mysql
Requires-Dist: pymysql>=1.1.0; extra == "mysql"
Requires-Dist: aiomysql>=0.2.0; extra == "mysql"
Provides-Extra: mssql
Requires-Dist: pyodbc>=5.0.0; extra == "mssql"
Provides-Extra: redis
Requires-Dist: redis>=5.0.0; extra == "redis"
Requires-Dist: hiredis>=2.0.0; extra == "redis"
Provides-Extra: all
Requires-Dist: psycopg2-binary>=2.9.0; extra == "all"
Requires-Dist: asyncpg>=0.29.0; extra == "all"
Requires-Dist: pymysql>=1.1.0; extra == "all"
Requires-Dist: aiomysql>=0.2.0; extra == "all"
Requires-Dist: pyodbc>=5.0.0; extra == "all"
Requires-Dist: redis>=5.0.0; extra == "all"
Requires-Dist: hiredis>=2.0.0; extra == "all"
Provides-Extra: dev
Requires-Dist: streamlit>=1.30.0; extra == "dev"
Requires-Dist: pytest>=8.4.2; extra == "dev"
Requires-Dist: pytest-asyncio>=1.2.0; extra == "dev"
Requires-Dist: black>=23.0.0; extra == "dev"
Requires-Dist: ruff>=0.1.0; extra == "dev"
Requires-Dist: mypy>=1.0.0; extra == "dev"
Requires-Dist: build>=1.3.0; extra == "dev"
Requires-Dist: twine>=6.2.0; extra == "dev"
Dynamic: license-file
Dynamic: requires-python
